codeboxapi/__init__.py
codeboxapi/api.py
codeboxapi/codebox.py
codeboxapi/docker.py
codeboxapi/local.py
codeboxapi/py.typed
codeboxapi/remote.py
codeboxapi/types.py
codeboxapi/utils.py
codeboxapi-0.2.6.dist-info/METADATA
codeboxapi-0.2.6.dist-info/WHEEL
codeboxapi-0.2.6.dist-info/entry_points.txt
codeboxapi-0.2.6.dist-info/licenses/LICENSE
codeboxapi-0.2.6.dist-info/RECORD
