Metadata-Version: 2.4
Name: codeboxapi
Version: 0.2.6
Summary: CodeBox gives you an easy scalable and isolated python interpreter for your LLM Agents.
Project-URL: repository, https://github.com/shroominic/codebox-api
Project-URL: api-reference, https://codeboxapi.com/docs
Project-URL: docs, https://codeboxapi.com/docs
Author-email: Shroominic <contact@shroominic.com>
License: MIT
License-File: LICENSE
Keywords: agent infrastructure,agent sandbox,agents,code sandbox,code-interpreter,codebox,codebox-api,codeboxapi,codeinterpreterapi,language model
Requires-Python: >=3.9
Requires-Dist: httpx>=0.27
Requires-Dist: tenacity>=9.0.0
Provides-Extra: all
Requires-Dist: aiofiles; extra == 'all'
Requires-Dist: bokeh; extra == 'all'
Requires-Dist: dash; extra == 'all'
Requires-Dist: fastapi[standard]; extra == 'all'
Requires-Dist: ipykernel; extra == 'all'
Requires-Dist: jupyter-client; extra == 'all'
Requires-Dist: matplotlib; extra == 'all'
Requires-Dist: networkx; extra == 'all'
Requires-Dist: numpy; extra == 'all'
Requires-Dist: openpyxl; extra == 'all'
Requires-Dist: pandas; extra == 'all'
Requires-Dist: pillow; extra == 'all'
Requires-Dist: plotly; extra == 'all'
Requires-Dist: python-docx; extra == 'all'
Requires-Dist: scikit-learn; extra == 'all'
Requires-Dist: scipy; extra == 'all'
Requires-Dist: seaborn; extra == 'all'
Requires-Dist: statsmodels; extra == 'all'
Requires-Dist: sympy; extra == 'all'
Requires-Dist: uv; extra == 'all'
Requires-Dist: yfinance; extra == 'all'
Provides-Extra: data-science
Requires-Dist: aiofiles; extra == 'data-science'
Requires-Dist: bokeh; extra == 'data-science'
Requires-Dist: dash; extra == 'data-science'
Requires-Dist: ipykernel; extra == 'data-science'
Requires-Dist: jupyter-client; extra == 'data-science'
Requires-Dist: matplotlib; extra == 'data-science'
Requires-Dist: networkx; extra == 'data-science'
Requires-Dist: numpy; extra == 'data-science'
Requires-Dist: openpyxl; extra == 'data-science'
Requires-Dist: pandas; extra == 'data-science'
Requires-Dist: pillow; extra == 'data-science'
Requires-Dist: plotly; extra == 'data-science'
Requires-Dist: python-docx; extra == 'data-science'
Requires-Dist: scikit-learn; extra == 'data-science'
Requires-Dist: scipy; extra == 'data-science'
Requires-Dist: seaborn; extra == 'data-science'
Requires-Dist: statsmodels; extra == 'data-science'
Requires-Dist: sympy; extra == 'data-science'
Requires-Dist: uv; extra == 'data-science'
Requires-Dist: yfinance; extra == 'data-science'
Provides-Extra: docs
Requires-Dist: mkdocs-material; extra == 'docs'
Requires-Dist: neoteroi-mkdocs; extra == 'docs'
Provides-Extra: local
Requires-Dist: aiofiles; extra == 'local'
Requires-Dist: ipykernel; extra == 'local'
Requires-Dist: jupyter-client; extra == 'local'
Requires-Dist: uv; extra == 'local'
Provides-Extra: pytest
Requires-Dist: pytest-asyncio; extra == 'pytest'
Provides-Extra: serve
Requires-Dist: fastapi[standard]; extra == 'serve'
Provides-Extra: vision
Requires-Dist: pillow; extra == 'vision'
